README.md
setup.cfg
setup.py
zpytrading/ZinnionAPI.py
zpytrading/__init__.py
zpytrading.egg-info/PKG-INFO
zpytrading.egg-info/SOURCES.txt
zpytrading.egg-info/dependency_links.txt
zpytrading.egg-info/requires.txt
zpytrading.egg-info/top_level.txt