Metadata-Version: 2.1
Name: zpytrading
Version: 0.0.9
Summary: Zinnion Streaming / Trading SDK
Home-page: https://github.com/Zinnion/zpytrading
Author: Mauro Delazeri
Author-email: mauro@zinnion.com
License: MIT
Download-URL: https://github.com/Zinnion/zpytrading/archive/v0.0.9.tar.gz
Keywords: zpytrading,zinnion,sdk,api
Platform: UNKNOWN
Classifier: Programming Language :: Python :: 3
Classifier: License :: OSI Approved :: MIT License
Classifier: Operating System :: OS Independent
